MANIFEST.in
README.rst
setup.py
incuna_storages/__init__.py
incuna_storages/models.py
incuna_storages.egg-info/PKG-INFO
incuna_storages.egg-info/SOURCES.txt
incuna_storages.egg-info/dependency_links.txt
incuna_storages.egg-info/not-zip-safe
incuna_storages.egg-info/top_level.txt
incuna_storages/backends/__init__.py
incuna_storages/backends/queued.py