Metadata-Version: 1.0
Name: incuna-storages
Version: 1.0
Summary: A collection of django storage backends.
Home-page: https://github.com/incuna/incuna-storages/
Author: Incuna Ltd
Author-email: admin@incuna.com
License: UNKNOWN
Platform: UNKNOWN
